twvideo_dl/__init__.py
twvideo_dl/main.py
twvideo_dl-0.0.2.dist-info/LICENSE.txt
twvideo_dl-0.0.2.dist-info/METADATA
twvideo_dl-0.0.2.dist-info/WHEEL
twvideo_dl-0.0.2.dist-info/entry_points.txt
twvideo_dl-0.0.2.dist-info/RECORD
